{
  "name": "Appuser",
  "fields": [
    {
      "fieldName": "creationDate",
      "fieldType": "Instant",
      "fieldValidateRules": ["required"]
    },
    {
      "fieldName": "bio",
      "fieldType": "String",
      "fieldValidateRules": ["maxlength"],
      "fieldValidateRulesMaxlength": "7500"
    },
    {
      "fieldName": "facebook",
      "fieldType": "String",
      "fieldValidateRules": ["maxlength"],
      "fieldValidateRulesMaxlength": "50"
    },
    {
      "fieldName": "twitter",
      "fieldType": "String",
      "fieldValidateRules": ["maxlength"],
      "fieldValidateRulesMaxlength": "50"
    },
    {
      "fieldName": "linkedin",
      "fieldType": "String",
      "fieldValidateRules": ["maxlength"],
      "fieldValidateRulesMaxlength": "50"
    },
    {
      "fieldName": "instagram",
      "fieldType": "String",
      "fieldValidateRules": ["maxlength"],
      "fieldValidateRulesMaxlength": "50"
    },
    {
      "fieldName": "birthdate",
      "fieldType": "Instant"
    }
  ],
  "relationships": [
    {
      "relationshipType": "one-to-one",
      "otherEntityName": "user",
      "otherEntityRelationshipName": "appuser",
      "relationshipValidateRules": "required",
      "relationshipName": "user",
      "otherEntityField": "id",
      "ownerSide": true
    },
    {
      "relationshipType": "one-to-many",
      "otherEntityName": "blog",
      "otherEntityRelationshipName": "appuser",
      "relationshipName": "blog",
      "otherEntityField": "title"
    },
    {
      "relationshipType": "one-to-many",
      "otherEntityName": "community",
      "otherEntityRelationshipName": "appuser",
      "relationshipName": "community"
    },
    {
      "relationshipType": "one-to-many",
      "otherEntityName": "notification",
      "otherEntityRelationshipName": "appuser",
      "relationshipName": "notification"
    },
    {
      "relationshipType": "one-to-many",
      "otherEntityName": "comment",
      "otherEntityRelationshipName": "appuser",
      "relationshipName": "comment"
    },
    {
      "relationshipType": "one-to-many",
      "otherEntityName": "post",
      "otherEntityRelationshipName": "appuser",
      "relationshipName": "post"
    },
    {
      "relationshipType": "one-to-many",
      "otherEntityName": "follow",
      "otherEntityRelationshipName": "followed",
      "relationshipName": "followed",
      "otherEntityField": "id"
    },
    {
      "relationshipType": "one-to-many",
      "otherEntityName": "follow",
      "otherEntityRelationshipName": "following",
      "relationshipName": "following",
      "otherEntityField": "id"
    },
    {
      "relationshipType": "one-to-many",
      "otherEntityName": "blockuser",
      "otherEntityRelationshipName": "blockeduser",
      "relationshipName": "blockeduser",
      "otherEntityField": "id"
    },
    {
      "relationshipType": "one-to-many",
      "otherEntityName": "blockuser",
      "otherEntityRelationshipName": "blockinguser",
      "relationshipName": "blockinguser",
      "otherEntityField": "id"
    },
    {
      "relationshipType": "one-to-one",
      "otherEntityName": "appphoto",
      "otherEntityRelationshipName": "appuser",
      "relationshipName": "appphoto",
      "otherEntityField": "id",
      "ownerSide": false
    },
    {
      "relationshipType": "many-to-many",
      "otherEntityName": "interest",
      "otherEntityRelationshipName": "appuser",
      "relationshipName": "interest",
      "otherEntityField": "interestName",
      "ownerSide": false
    },
    {
      "relationshipType": "many-to-many",
      "otherEntityName": "activity",
      "otherEntityRelationshipName": "appuser",
      "relationshipName": "activity",
      "otherEntityField": "activityName",
      "ownerSide": false
    },
    {
      "relationshipType": "many-to-many",
      "otherEntityName": "celeb",
      "otherEntityRelationshipName": "appuser",
      "relationshipName": "celeb",
      "otherEntityField": "celebName",
      "ownerSide": false
    }
  ],
  "entityTableName": "appuser",
  "dto": "mapstruct",
  "pagination": "pagination",
  "service": "serviceImpl",
  "jpaMetamodelFiltering": true,
  "fluentMethods": true,
  "readOnly": false,
  "embedded": false,
  "applications": "*",
  "changelogDate": "20210511094615"
}
